hop3/__init__.py
hop3/actors/__init__.py
hop3/actors/actor.py
hop3/actors/mailbox/__init__.py
hop3/actors/mailbox/base.py
hop3/actors/mailbox/ipc.py
hop3/actors/mailbox/kombu.py
hop3/actors/mailbox/local.py
hop3/actors/mailbox/sqs.py
hop3/actors/mailbox/tcp.py
hop3/actors/mailbox/zmq.py
hop3/actors/message.py
hop3/addons/__init__.py
hop3/addons/base.py
hop3/addons/postgres.py
hop3/builders/__init__.py
hop3/builders/base.py
hop3/builders/clojure.py
hop3/builders/go.py
hop3/builders/java.py
hop3/builders/node.py
hop3/builders/php.py
hop3/builders/python.py
hop3/builders/ruby.py
hop3/builders/rust.py
hop3/builders/util.py
hop3/commands/__init__.py
hop3/commands/apps.py
hop3/commands/cli.py
hop3/commands/config.py
hop3/commands/git.py
hop3/commands/misc.py
hop3/commands/plugins/__init__.py
hop3/commands/plugins/postgresql.py
hop3/commands/plugins/redis.py
hop3/commands/setup.py
hop3/commands/util.py
hop3/core/__init__.py
hop3/core/app.py
hop3/core/env.py
hop3/core/events.py
hop3/core/hookspecs.py
hop3/core/plugins.py
hop3/core/types.py
hop3/deploy.py
hop3/main.py
hop3/model/__init__.py
hop3/model/app.py
hop3/model/backup.py
hop3/model/base.py
hop3/model/env.py
hop3/model/instance.py
hop3/model/security.py
hop3/oses/__init__.py
hop3/oses/common.py
hop3/oses/debian.py
hop3/oses/debian12.py
hop3/oses/helpers.py
hop3/oses/nixos.py
hop3/oses/ubuntu2204.py
hop3/project/__init__.py
hop3/project/config.py
hop3/project/procfile.py
hop3/proxies/__init__.py
hop3/proxies/nginx/__init__.py
hop3/proxies/nginx/certificates.py
hop3/proxies/nginx/setup.py
hop3/proxies/nginx/templates.py
hop3/run/__init__.py
hop3/run/spawn.py
hop3/run/uwsgi/__init__.py
hop3/run/uwsgi/settings.py
hop3/run/uwsgi/test_settings.py
hop3/run/uwsgi/worker.py
hop3/services/__init__.py
hop3/services/config.py
hop3/svcs.py
hop3/system/__init__.py
hop3/system/config.py
hop3/system/constants.py
hop3/system/state.py
hop3/testing/__init__.py
hop3/testing/base.py
hop3/testing/common.py
hop3/testing/main.py
hop3-0.2.2.dist-info/LICENSE.txt
hop3-0.2.2.dist-info/LICENSES/AGPL-3.0-only.txt
hop3-0.2.2.dist-info/LICENSES/BSD-3-Clause.txt
hop3-0.2.2.dist-info/LICENSES/CC-BY-4.0.txt
hop3-0.2.2.dist-info/LICENSES/CC0-1.0.txt
hop3-0.2.2.dist-info/LICENSES/MIT.txt
hop3-0.2.2.dist-info/METADATA
hop3-0.2.2.dist-info/WHEEL
hop3-0.2.2.dist-info/entry_points.txt
hop3-0.2.2.dist-info/RECORD
