Metadata-Version: 2.1
Name: hop3
Version: 0.2.2
Summary: Simple PaaS - Deploy and manage web applications on a single server
Author: Stefane Fermigier
Author-email: sf@abilian.com
Requires-Python: >=3.10,<4.0
Classifier: Programming Language :: Python :: 3
Classifier: Programming Language :: Python :: 3.10
Classifier: Programming Language :: Python :: 3.11
Classifier: Programming Language :: Python :: 3.12
Requires-Dist: advanced-alchemy (>=0.17,<0.18)
Requires-Dist: attrs
Requires-Dist: cleez
Requires-Dist: click (>=8.1.7,<9.0.0)
Requires-Dist: cloudpickle (>=3.0.0,<4.0.0)
Requires-Dist: devtools (>=0.12.2,<0.13.0)
Requires-Dist: eventlet (>=0.36,<0.37)
Requires-Dist: flask (>=3.0.3,<4.0.0)
Requires-Dist: flask-babel (>=4.0.0,<5.0.0)
Requires-Dist: flask-htmx (>=0.3.2,<0.4.0)
Requires-Dist: flask-mail (>=0.10.0,<0.11.0)
Requires-Dist: flask-migrate (>=4.0.7,<5.0.0)
Requires-Dist: flask-security-too (>=5.4.3,<6.0.0)
Requires-Dist: flask-sqlalchemy (>=3.1.1,<4.0.0)
Requires-Dist: flask-super (>=0.2.8,<0.3.0)
Requires-Dist: flask-talisman (>=1.1.0,<2.0.0)
Requires-Dist: flask-vite (>=0.5.0,<0.6.0)
Requires-Dist: msgpack (>=1.0.8,<2.0.0)
Requires-Dist: pluggy (>=1.4.0,<2.0.0)
Requires-Dist: psycopg2 (>=2.9.9,<3.0.0)
Requires-Dist: pyrsistent (>=0.20.0,<0.21.0)
Requires-Dist: pyzmq (>=26,<27)
Requires-Dist: snoop (>=0.4.3,<0.5.0)
Requires-Dist: sqlalchemy (>=2.0.29,<3.0.0)
Requires-Dist: sqlalchemy-serializer (>=1.4.12,<2.0.0)
Requires-Dist: sqlalchemy-utils (>=0.41.2,<0.42.0)
Requires-Dist: svcs (>=24.1.0,<25.0.0)
